pyparsebluray/__init__.py
pyparsebluray/py.typed
pyparsebluray/mpls/__init__.py
pyparsebluray/mpls/app_info_playlist.py
pyparsebluray/mpls/extension_data.py
pyparsebluray/mpls/load.py
pyparsebluray/mpls/movie_playlist.py
pyparsebluray/mpls/play_item.py
pyparsebluray/mpls/playlist.py
pyparsebluray/mpls/playlist_mark.py
pyparsebluray/mpls/sub_path.py
pyparsebluray-0.1.4.dist-info/LICENSE
pyparsebluray-0.1.4.dist-info/METADATA
pyparsebluray-0.1.4.dist-info/WHEEL
pyparsebluray-0.1.4.dist-info/top_level.txt
pyparsebluray-0.1.4.dist-info/RECORD
