Metadata-Version: 2.1
Name: pyparsebluray
Version: 0.1.4
Summary: Parse and extract binary data from bluray files
Home-page: https://github.com/Ichunjo/pyparsebluray
Author: Vardë
Author-email: ichunjo.le.terrible@gmail.com
License: UNKNOWN
Platform: UNKNOWN
Classifier: Intended Audience :: Developers
Classifier: Programming Language :: Python :: 3
Classifier: License :: OSI Approved :: MIT License
Classifier: Operating System :: OS Independent
Requires-Python: >=3.9
License-File: LICENSE
